h2o_featurestore/__init__.py
h2o_featurestore/version.txt
h2o_featurestore/core/__init__.py
h2o_featurestore/core/access_modifier.py
h2o_featurestore/core/access_type.py
h2o_featurestore/core/acl.py
h2o_featurestore/core/browser.py
h2o_featurestore/core/client.py
h2o_featurestore/core/config.py
h2o_featurestore/core/config_utils.py
h2o_featurestore/core/connection_config.py
h2o_featurestore/core/credentials.py
h2o_featurestore/core/dashboard.py
h2o_featurestore/core/data_source_wrappers.py
h2o_featurestore/core/data_types.py
h2o_featurestore/core/feature_set_flow.py
h2o_featurestore/core/featurestore_client.py
h2o_featurestore/core/interactive_console.py
h2o_featurestore/core/job_info.py
h2o_featurestore/core/job_type.py
h2o_featurestore/core/logging.py
h2o_featurestore/core/retrieve_holder.py
h2o_featurestore/core/review_statuses.py
h2o_featurestore/core/schema.py
h2o_featurestore/core/search_field.py
h2o_featurestore/core/search_operator.py
h2o_featurestore/core/storage_optimization.py
h2o_featurestore/core/transformations.py
h2o_featurestore/core/user_credentials.py
h2o_featurestore/core/utils.py
h2o_featurestore/core/auth/__init__.py
h2o_featurestore/core/auth/auth.py
h2o_featurestore/core/auth/pat_token_provider.py
h2o_featurestore/core/auth/token_api_client.py
h2o_featurestore/core/collections/admin_projects.py
h2o_featurestore/core/collections/artifacts.py
h2o_featurestore/core/collections/classifiers.py
h2o_featurestore/core/collections/feature_set_reviews.py
h2o_featurestore/core/collections/feature_sets.py
h2o_featurestore/core/collections/ingest_history.py
h2o_featurestore/core/collections/jobs.py
h2o_featurestore/core/collections/pats.py
h2o_featurestore/core/collections/projects.py
h2o_featurestore/core/collections/scheduled_tasks.py
h2o_featurestore/core/commons/__init__.py
h2o_featurestore/core/commons/case_insensitive_dict.py
h2o_featurestore/core/commons/spark_utils.py
h2o_featurestore/core/entities/__init__.py
h2o_featurestore-2.3.1.dist-info/METADATA
h2o_featurestore-2.3.1.dist-info/WHEEL
h2o_featurestore-2.3.1.dist-info/RECORD
