Metadata-Version: 2.4
Name: h2o_featurestore
Version: 2.3.1
Summary: Python client for H2O Feature Store
Project-URL: Documentation, https://docs.h2o.ai/featurestore/api/permissions
Author-email: "H2O.ai" <support@h2o.ai>
Requires-Python: >=3.8
Requires-Dist: h2o-authn>=1.0.0
Requires-Dist: h2o-cloud-discovery>=2.1.0
Requires-Dist: jproperties>=2.1.2
Requires-Dist: packaging>=25.0
Requires-Dist: python-dateutil>=2.8.2
Requires-Dist: requests>=2.26.0
Requires-Dist: typing-extensions>=4.7.1
Requires-Dist: tzlocal>=5.3.1
